aiosignal/__init__.py
aiosignal/__init__.pyi
aiosignal/py.typed
aiosignal-1.1.2.dist-info/LICENSE.txt
aiosignal-1.1.2.dist-info/METADATA
aiosignal-1.1.2.dist-info/WHEEL
aiosignal-1.1.2.dist-info/top_level.txt
aiosignal-1.1.2.dist-info/RECORD
