Metadata-Version: 2.1
Name: aiosignal
Version: 1.1.2
Summary: aiosignal: a list of registered asynchronous callbacks
Home-page: https://github.com/aio-libs/aiosignal
Author: Nikolay Kim
Author-email: fafhrd91@gmail.com
Maintainer: Martijn Pieters <mj@zopatista.com>
Maintainer-email: aio-libs@googlegroups.com
License: Apache 2
Project-URL: Chat: Gitter, https://gitter.im/aio-libs/Lobby
Project-URL: CI: GitHub Actions, https://github.com/aio-libs/aiosignal/actions
Project-URL: Coverage: codecov, https://codecov.io/github/aio-libs/aiosignal
Project-URL: Docs: RTD, https://docs.aiosignal.org
Project-URL: GitHub: issues, https://github.com/aio-libs/aiosignal/issues
Project-URL: GitHub: repo, https://github.com/aio-libs/aiosignal
Platform: UNKNOWN
Classifier: License :: OSI Approved :: Apache Software License
Classifier: Intended Audience :: Developers
Classifier: Programming Language :: Python
Classifier: Programming Language :: Python :: 3
Classifier: Programming Language :: Python :: 3.6
Classifier: Programming Language :: Python :: 3.7
Classifier: Programming Language :: Python :: 3.8
Classifier: Programming Language :: Python :: 3.9
Classifier: Development Status :: 5 - Production/Stable
Classifier: Operating System :: POSIX
Classifier: Operating System :: MacOS :: MacOS X
Classifier: Operating System :: Microsoft :: Windows
Classifier: Framework :: AsyncIO
Requires-Python: >=3.6
Requires-Dist: frozenlist (>=1.1.0)
